ax3_mixins/__init__.py
ax3_mixins/mixins.py
AX3_Mixins-1.0.1.dist-info/LICENSE
AX3_Mixins-1.0.1.dist-info/METADATA
AX3_Mixins-1.0.1.dist-info/WHEEL
AX3_Mixins-1.0.1.dist-info/top_level.txt
AX3_Mixins-1.0.1.dist-info/RECORD
