Metadata-Version: 2.1
Name: AX3-Mixins
Version: 1.0.1
Summary: Mixins for use into the AX3 tech stack
Home-page: https://github.com/axiacore/ax3-mixins
Author: Axiacore
Author-email: info@axiacore.com
License: UNKNOWN
Platform: UNKNOWN
Classifier: Programming Language :: Python :: 3.8
Classifier: License :: OSI Approved :: MIT License
Classifier: Operating System :: OS Independent
